{
  "cache" : {
    "PN2-167.114.104.115" : {
      "invalidDomains" : {
        "simprosys.com" : "Thu Jul 01 18:16:34 IST 2021",
        "goldcoastlimos.com" : "Thu Jul 01 18:16:46 IST 2021",
        "air7seas.us" : "Thu Jul 01 18:16:34 IST 2021",
        "ronandsonstrucking.com" : "Thu Jul 01 18:16:34 IST 2021",
        "sterlingtransportation.com" : "Thu Jul 01 18:14:44 IST 2021",
        "unitedchb.com" : "Thu Jul 01 18:16:33 IST 2021",
        "wvlcorp.com" : "Thu Jul 01 18:16:34 IST 2021",
        "clearfreight.com" : "Thu Jul 01 18:16:46 IST 2021",
        "nlstrans.com" : "Thu Jul 01 18:16:58 IST 2021",
        "pacifictank.net" : "Thu Jul 01 18:14:44 IST 2021",
        "aclifts.com" : "Thu Jul 01 18:16:58 IST 2021",
        "dwmorgan.com" : "Thu Jul 01 18:16:34 IST 2021",
        "transgroup.com" : "Thu Jul 01 18:16:33 IST 2021",
        "alaskaair.com" : "Thu Jul 01 18:16:34 IST 2021",
        "seqirus.com" : "Thu Jul 01 18:16:46 IST 2021",
        "quali-t-ruck.com" : "Thu Jul 01 18:16:46 IST 2021",
        "pac-ocean.com" : "Thu Jul 01 18:16:34 IST 2021",
        "state.ca.gov" : "Thu Jul 01 18:16:34 IST 2021",
        "eclectictour.com" : "Thu Jul 01 18:16:46 IST 2021",
        "ironcompany.com" : "Thu Jul 01 18:16:58 IST 2021",
        "abtruck.com" : "Thu Jul 01 18:16:34 IST 2021",
        "piazzatrucking.com" : "Thu Jul 01 18:16:34 IST 2021",
        "metabuy.com" : "Thu Jul 01 18:16:46 IST 2021",
        "aroundav.com" : "Thu Jul 01 18:16:33 IST 2021",
        "aerologistics.net" : "Thu Jul 01 18:16:34 IST 2021",
        "sunline.org" : "Thu Jul 01 18:14:45 IST 2021",
        "lindbycustom.com" : "Thu Jul 01 18:16:58 IST 2021",
        "helimaxaviation.net" : "Thu Jul 01 18:16:46 IST 2021",
        "ontrac.com" : "Thu Jul 01 18:14:44 IST 2021",
        "californiamoving.com" : "Thu Jul 01 18:16:34 IST 2021",
        "pcc.com" : "Thu Jul 01 18:16:46 IST 2021",
        "dougveerkamp.com" : "Thu Jul 01 18:16:34 IST 2021",
        "ontimepermits.com" : "Thu Jul 01 18:16:46 IST 2021",
        "avsta.com" : "Thu Jul 01 18:16:58 IST 2021",
        "acontainers.com" : "Thu Jul 01 18:16:34 IST 2021",
        "afterfivelimousines.com" : "Thu Jul 01 18:16:34 IST 2021",
        "jplogistics.net" : "Thu Jul 01 18:16:33 IST 2021",
        "cybercity3d.com" : "Thu Jul 01 18:16:34 IST 2021",
        "alltowntransport.com" : "Thu Jul 01 18:14:45 IST 2021",
        "orbicair.com" : "Thu Jul 01 18:16:34 IST 2021",
        "graebel.com" : "Thu Jul 01 18:16:46 IST 2021",
        "amadortransit.com" : "Thu Jul 01 18:16:46 IST 2021",
        "bradysmoving.com" : "Thu Jul 01 18:16:34 IST 2021",
        "hawaiianexpressinc.com" : "Thu Jul 01 18:16:33 IST 2021",
        "wcspermits.com" : "Thu Jul 01 18:16:33 IST 2021",
        "losangeleslimousine.com" : "Thu Jul 01 18:14:45 IST 2021",
        "2eastwest.com" : "Thu Jul 01 18:14:45 IST 2021",
        "bestlogistics.net" : "Thu Jul 01 18:16:46 IST 2021",
        "executours.com" : "Thu Jul 01 18:16:34 IST 2021",
        "jfmoran.com" : "Thu Jul 01 18:16:34 IST 2021",
        "jpinstruments.com" : "Thu Jul 01 18:16:34 IST 2021",
        "mercuryair.com" : "Thu Jul 01 18:16:34 IST 2021",
        "watersmoving.com" : "Thu Jul 01 18:16:33 IST 2021",
        "unicoldcorp.com" : "Thu Jul 01 18:14:45 IST 2021",
        "tsllc.com" : "Thu Jul 01 18:16:33 IST 2021",
        "ggiant.com" : "Thu Jul 01 18:16:46 IST 2021",
        "macymovers.com" : "Thu Jul 01 18:14:45 IST 2021",
        "landstar.com" : "Thu Jul 01 18:16:58 IST 2021",
        "loomistank.com" : "Thu Jul 01 18:16:34 IST 2021",
        "coastallivery.com" : "Thu Jul 01 18:16:33 IST 2021",
        "distinctiverecognition.com" : "Thu Jul 01 18:16:45 IST 2021",
        "mccollisters.com" : "Thu Jul 01 18:16:57 IST 2021",
        "ablefreight.com" : "Thu Jul 01 18:16:34 IST 2021",
        "calstar.org" : "Thu Jul 01 18:16:46 IST 2021",
        "packair.com" : "Thu Jul 01 18:16:34 IST 2021",
        "centurywestlimo.com" : "Thu Jul 01 18:14:45 IST 2021",
        "brittoncompany.com" : "Thu Jul 01 18:16:46 IST 2021",
        "foxrep.com" : "Thu Jul 01 18:14:45 IST 2021",
        "tacustoms.com" : "Thu Jul 01 18:16:58 IST 2021",
        "masterpieceintl.com" : "Thu Jul 01 18:16:33 IST 2021",
        "jetproinc.com" : "Thu Jul 01 18:14:45 IST 2021",
        "norcalambulance.com" : "Thu Jul 01 18:16:34 IST 2021",
        "nmvb.ca.gov" : "Thu Jul 01 18:16:34 IST 2021",
        "actionfreightinc.com" : "Thu Jul 01 18:16:34 IST 2021",
        "pghwong.com" : "Thu Jul 01 18:16:34 IST 2021",
        "brackeninc.com" : "Thu Jul 01 18:16:34 IST 2021",
        "omnilogistics.com" : "Thu Jul 01 18:16:34 IST 2021",
        "algworldwide.com" : "Thu Jul 01 18:16:46 IST 2021",
        "butchcamerontrucking.com" : "Thu Jul 01 18:16:46 IST 2021",
        "calstarmessenger.com" : "Thu Jul 01 18:14:45 IST 2021",
        "tomsmovers.com" : "Thu Jul 01 18:16:46 IST 2021",
        "cachecanyon.com" : "Thu Jul 01 18:14:45 IST 2021",
        "rlttrucking.com" : "Thu Jul 01 18:16:34 IST 2021",
        "globexship.com" : "Thu Jul 01 18:16:46 IST 2021",
        "filmocracy.com" : "Thu Jul 01 18:14:45 IST 2021",
        "ticketmedia.com" : "Thu Jul 01 18:16:34 IST 2021",
        "rapidexpressonline.com" : "Thu Jul 01 18:16:33 IST 2021",
        "peoplecap.com" : "Thu Jul 01 18:16:34 IST 2021",
        "astigmatic.com" : "Thu Jul 01 18:16:46 IST 2021",
        "gtscharter.com" : "Thu Jul 01 18:16:34 IST 2021",
        "traffictech.com" : "Thu Jul 01 18:16:46 IST 2021",
        "goldeneaglemoving.com" : "Thu Jul 01 18:16:34 IST 2021",
        "kkwtrucks.com" : "Thu Jul 01 18:16:46 IST 2021",
        "topviptransportation.com" : "Thu Jul 01 18:16:34 IST 2021",
        "trinityriverrafting.com" : "Thu Jul 01 18:16:33 IST 2021",
        "transcore.com" : "Thu Jul 01 18:16:34 IST 2021",
        "gotodcd.com" : "Thu Jul 01 18:14:45 IST 2021",
        "artgecko.com" : "Thu Jul 01 18:16:46 IST 2021",
        "facilitieslogistics.com" : "Thu Jul 01 18:14:45 IST 2021",
        "gmail.com" : "Thu Jul 01 18:16:34 IST 2021",
        "bekinssantarosa.com" : "Thu Jul 01 18:16:46 IST 2021",
        "jetdelivery.com" : "Thu Jul 01 18:16:33 IST 2021",
        "caroleandjans.com" : "Thu Jul 01 18:14:45 IST 2021",
        "northernrefrigerated.com" : "Thu Jul 01 18:16:46 IST 2021",
        "redroselimos.com" : "Thu Jul 01 18:16:34 IST 2021",
        "lawrencefinearts.com" : "Thu Jul 01 18:14:45 IST 2021",
        "pianomoves.com" : "Thu Jul 01 18:16:46 IST 2021",
        "clockworkexpress.com" : "Thu Jul 01 18:16:58 IST 2021",
        "aieinc.com" : "Thu Jul 01 18:16:34 IST 2021",
        "riverrunnersusa.com" : "Thu Jul 01 18:16:34 IST 2021",
        "livingstonintl.com" : "Thu Jul 01 18:16:46 IST 2021",
        "yachtcharter.com" : "Thu Jul 01 18:16:33 IST 2021",
        "pyramid-logistics.com" : "Thu Jul 01 18:16:33 IST 2021",
        "jetpets.com" : "Thu Jul 01 18:16:34 IST 2021",
        "omegamoving.com" : "Thu Jul 01 18:16:34 IST 2021",
        "pods.com" : "Thu Jul 01 18:16:46 IST 2021",
        "apluslimos.com" : "Thu Jul 01 18:16:46 IST 2021",
        "airliftusa.com" : "Thu Jul 01 18:16:33 IST 2021",
        "sbmtd.gov" : "Thu Jul 01 18:16:34 IST 2021",
        "manilaforwarder.com" : "Thu Jul 01 18:16:46 IST 2021",
        "ilsinc.net" : "Thu Jul 01 18:16:33 IST 2021",
        "traillines.com" : "Thu Jul 01 18:16:34 IST 2021",
        "whitewatervoyages.com" : "Thu Jul 01 18:14:44 IST 2021",
        "globalshippers.com" : "Thu Jul 01 18:16:46 IST 2021",
        "ocsport.com" : "Thu Jul 01 18:16:34 IST 2021",
        "nasam.com" : "Thu Jul 01 18:14:44 IST 2021",
        "limoclub.com" : "Thu Jul 01 18:16:46 IST 2021",
        "themeansar.com" : "Thu Jul 01 18:16:46 IST 2021",
        "preferredcharters.com" : "Thu Jul 01 18:16:46 IST 2021",
        "sebringtransport.com" : "Thu Jul 01 18:16:34 IST 2021",
        "nmsmoving.com" : "Thu Jul 01 18:14:44 IST 2021",
        "empirecls.com" : "Thu Jul 01 18:16:46 IST 2021",
        "myamericanmovers.com" : "Thu Jul 01 18:16:58 IST 2021",
        "rebelvanlines.com" : "Thu Jul 01 18:16:34 IST 2021",
        "tshow.com" : "Thu Jul 01 18:16:34 IST 2021",
        "lynch-ems.com" : "Thu Jul 01 18:14:45 IST 2021",
        "siriani.com" : "Thu Jul 01 18:14:44 IST 2021",
        "petrobuilders.com" : "Thu Jul 01 18:16:58 IST 2021",
        "slocog.org" : "Thu Jul 01 18:14:44 IST 2021",
        "rottenrobbie.com" : "Thu Jul 01 18:16:34 IST 2021",
        "marintransit.org" : "Thu Jul 01 18:16:34 IST 2021",
        "ibttruck.com" : "Thu Jul 01 18:16:34 IST 2021",
        "cmrstrainclub.org" : "Thu Jul 01 18:16:34 IST 2021",
        "megavanlines.com" : "Thu Jul 01 18:16:34 IST 2021",
        "calaircargo.com" : "Thu Jul 01 18:16:34 IST 2021",
        "dfreight.com" : "Thu Jul 01 18:16:34 IST 2021",
        "dksassociates.com" : "Thu Jul 01 18:16:34 IST 2021",
        "cargolux.com" : "Thu Jul 01 18:16:34 IST 2021",
        "readytoroll.com" : "Thu Jul 01 18:14:45 IST 2021",
        "arrafting.com" : "Thu Jul 01 18:14:44 IST 2021",
        "carrytransit.com" : "Thu Jul 01 18:16:46 IST 2021",
        "shamrockmovingstorage.com" : "Thu Jul 01 18:16:34 IST 2021",
        "becequipment.com" : "Thu Jul 01 18:16:34 IST 2021",
        "shipoverseas.com" : "Thu Jul 01 18:16:34 IST 2021",
        "spi-inc.com" : "Thu Jul 01 18:16:34 IST 2021",
        "rescuedelivery.com" : "Thu Jul 01 18:16:34 IST 2021",
        "uartinc.com" : "Thu Jul 01 18:16:34 IST 2021",
        "sky2c.com" : "Thu Jul 01 18:16:34 IST 2021",
        "arta.org" : "Thu Jul 01 18:16:34 IST 2021",
        "medicalsupplies.mx" : "Thu Jul 01 18:16:34 IST 2021",
        "myplinc.com" : "Thu Jul 01 18:14:45 IST 2021",
        "sullivanunited.com" : "Thu Jul 01 18:16:34 IST 2021",
        "graysonfreight.com" : "Thu Jul 01 18:16:34 IST 2021",
        "riolo.com" : "Thu Jul 01 18:16:34 IST 2021",
        "ccwinetours.com" : "Thu Jul 01 18:16:34 IST 2021",
        "rubiconadventures.com" : "Thu Jul 01 18:14:45 IST 2021",
        "comcast.net" : "Thu Jul 01 18:16:33 IST 2021",
        "coworker.com" : "Thu Jul 01 18:16:34 IST 2021",
        "hallamb.com" : "Thu Jul 01 18:16:34 IST 2021",
        "movetopia.com" : "Thu Jul 01 18:16:46 IST 2021",
        "pinkdot.com" : "Thu Jul 01 18:16:33 IST 2021",
        "twomen.com" : "Thu Jul 01 18:16:34 IST 2021",
        "montcc.com" : "Thu Jul 01 18:16:34 IST 2021",
        "freightforce.com" : "Thu Jul 01 18:14:45 IST 2021",
        "desertairambulance.com" : "Thu Jul 01 18:16:34 IST 2021",
        "intexpress.com" : "Thu Jul 01 18:16:46 IST 2021",
        "omnitrax.com" : "Thu Jul 01 18:14:45 IST 2021",
        "confiancalogistics.com" : "Thu Jul 01 18:16:34 IST 2021",
        "crownxt.com" : "Thu Jul 01 18:14:45 IST 2021",
        "ttllogistics.com" : "Thu Jul 01 18:16:46 IST 2021",
        "magnumwinetours.com" : "Thu Jul 01 18:16:33 IST 2021",
        "aplustours.com" : "Thu Jul 01 18:16:33 IST 2021",
        "approvedforwarders.com" : "Thu Jul 01 18:14:45 IST 2021",
        "saycargo.com" : "Thu Jul 01 18:16:46 IST 2021",
        "hawaiianexpress.com" : "Thu Jul 01 18:16:33 IST 2021",
        "bettendorftrucking.com" : "Thu Jul 01 18:16:34 IST 2021",
        "ballparkpedicabs.com" : "Thu Jul 01 18:14:45 IST 2021",
        "friendsoftheriver.org" : "Thu Jul 01 18:16:34 IST 2021",
        "sandiegowedding.com" : "Thu Jul 01 18:16:34 IST 2021",
        "ishilimo.com" : "Thu Jul 01 18:14:45 IST 2021",
        "blslimo.com" : "Thu Jul 01 18:16:34 IST 2021",
        "alliancechb.com" : "Thu Jul 01 18:16:34 IST 2021",
        "preslimo.com" : "Thu Jul 01 18:16:34 IST 2021",
        "flexivan.com" : "Thu Jul 01 18:14:45 IST 2021",
        "luckymoving.com.tw" : "Thu Jul 01 18:16:34 IST 2021",
        "eclamericas.com" : "Thu Jul 01 18:16:46 IST 2021",
        "weyerhaeuser.com" : "Thu Jul 01 18:14:45 IST 2021",
        "traveltown.org" : "Thu Jul 01 18:16:46 IST 2021",
        "gel.com" : "Thu Jul 01 18:16:34 IST 2021",
        "boatswainslocker.com" : "Thu Jul 01 18:16:46 IST 2021",
        "melrosemoving.com" : "Thu Jul 01 18:16:33 IST 2021",
        "vvta.org" : "Thu Jul 01 18:16:34 IST 2021",
        "aaronsmoving.com" : "Thu Jul 01 18:16:34 IST 2021",
        "onehour.net" : "Thu Jul 01 18:16:34 IST 2021",
        "plyconvanlines.com" : "Thu Jul 01 18:16:46 IST 2021",
        "shipsmart.com" : "Thu Jul 01 18:16:34 IST 2021",
        "regarrison.com" : "Thu Jul 01 18:16:34 IST 2021",
        "paramountlimo.com" : "Thu Jul 01 18:16:34 IST 2021",
        "marken.com" : "Thu Jul 01 18:16:58 IST 2021",
        "nlslimo.com" : "Thu Jul 01 18:14:45 IST 2021",
        "aavems.com" : "Thu Jul 01 18:16:34 IST 2021",
        "travellimo.com" : "Thu Jul 01 18:16:33 IST 2021",
        "mayersd.com" : "Thu Jul 01 18:16:33 IST 2021",
        "jelinek.com" : "Thu Jul 01 18:16:34 IST 2021",
        "mxpresstrans.com" : "Thu Jul 01 18:16:34 IST 2021",
        "spectrumotion.com" : "Thu Jul 01 18:16:33 IST 2021",
        "lacostalimo.com" : "Thu Jul 01 18:16:34 IST 2021",
        "limochartersusa.com" : "Thu Jul 01 18:16:46 IST 2021",
        "netlogistics.com" : "Thu Jul 01 18:16:33 IST 2021",
        "lowermybills.com" : "Thu Jul 01 18:16:34 IST 2021",
        "wetzelmoving.com" : "Thu Jul 01 18:16:34 IST 2021",
        "goldrushexpress.com" : "Thu Jul 01 18:16:33 IST 2021",
        "unitedshipping.com" : "Thu Jul 01 18:16:33 IST 2021",
        "ucltd.com" : "Thu Jul 01 18:16:46 IST 2021",
        "datstrucking.com" : "Thu Jul 01 18:14:44 IST 2021",
        "calaverastransit.com" : "Thu Jul 01 18:14:44 IST 2021",
        "securitysafeusa.com" : "Thu Jul 01 18:16:58 IST 2021",
        "viptransport.com" : "Thu Jul 01 18:16:34 IST 2021",
        "movefreight.com" : "Thu Jul 01 18:16:34 IST 2021",
        "rockstarsb.com" : "Thu Jul 01 18:14:44 IST 2021",
        "tplusa.com" : "Thu Jul 01 18:16:34 IST 2021",
        "classiclimos.com" : "Thu Jul 01 18:14:44 IST 2021",
        "americanbest.com" : "Thu Jul 01 18:16:34 IST 2021",
        "cpanel.net" : "Thu Jul 01 18:16:34 IST 2021",
        "momentumlog.com" : "Thu Jul 01 18:16:46 IST 2021",
        "eapreferredcarservice.com" : "Thu Jul 01 18:14:44 IST 2021",
        "dave.com" : "Thu Jul 01 18:16:34 IST 2021",
        "mrorange.com" : "Thu Jul 01 18:14:44 IST 2021",
        "swankconstructioninc.com" : "Thu Jul 01 18:16:34 IST 2021",
        "ablecargo.com" : "Thu Jul 01 18:16:46 IST 2021",
        "mosaicglobaltransportation.com" : "Thu Jul 01 18:14:44 IST 2021",
        "mvtransit.com" : "Thu Jul 01 18:14:44 IST 2021",
        "trance4u.com" : "Thu Jul 01 18:16:46 IST 2021",
        "amstarexpress.com" : "Thu Jul 01 18:16:33 IST 2021",
        "aviplimo.com" : "Thu Jul 01 18:16:34 IST 2021",
        "newslogistics.net" : "Thu Jul 01 18:16:34 IST 2021",
        "alexanders.net" : "Thu Jul 01 18:16:34 IST 2021",
        "jensonlogistics.com" : "Thu Jul 01 18:16:33 IST 2021",
        "eventswest.us" : "Thu Jul 01 18:16:46 IST 2021",
        "farnsworthexpress.com" : "Thu Jul 01 18:16:34 IST 2021",
        "conciergelimo.com" : "Thu Jul 01 18:14:45 IST 2021",
        "roadexamerica.com" : "Thu Jul 01 18:16:34 IST 2021",
        "msn.com" : "Thu Jul 01 18:16:33 IST 2021",
        "merittrucking.com" : "Thu Jul 01 18:14:45 IST 2021",
        "tahoeraft.com" : "Thu Jul 01 18:16:33 IST 2021",
        "ccta.net" : "Thu Jul 01 18:16:34 IST 2021",
        "cusonet.com" : "Thu Jul 01 18:16:46 IST 2021",
        "gwtrans.com" : "Thu Jul 01 18:16:45 IST 2021",
        "rainforrent.com" : "Thu Jul 01 18:16:46 IST 2021",
        "sbcounty.gov" : "Thu Jul 01 18:16:33 IST 2021",
        "sfcta.org" : "Thu Jul 01 18:16:34 IST 2021",
        "u-pic.com" : "Thu Jul 01 18:16:46 IST 2021",
        "lexmardistribution.com" : "Thu Jul 01 18:16:34 IST 2021",
        "northbaymoving.com" : "Thu Jul 01 18:16:34 IST 2021",
        "popeyemoving.com" : "Thu Jul 01 18:16:34 IST 2021",
        "cosmoexpress.com" : "Thu Jul 01 18:16:34 IST 2021",
        "mjbfreight.com" : "Thu Jul 01 18:16:46 IST 2021",
        "prioritymoving.com" : "Thu Jul 01 18:14:45 IST 2021",
        "aasphalt.com" : "Thu Jul 01 18:16:34 IST 2021",
        "oceaninstruments.com" : "Thu Jul 01 18:16:33 IST 2021",
        "skylarklimo.com" : "Thu Jul 01 18:14:45 IST 2021",
        "vectormedia.com" : "Thu Jul 01 18:16:34 IST 2021",
        "valdophye.com" : "Thu Jul 01 18:16:58 IST 2021",
        "minutemantransport.com" : "Thu Jul 01 18:16:33 IST 2021",
        "pedalexpress.com" : "Thu Jul 01 18:16:33 IST 2021",
        "westair.net" : "Thu Jul 01 18:16:46 IST 2021",
        "servicewest.com" : "Thu Jul 01 18:14:45 IST 2021",
        "tradeshowtrish.com" : "Thu Jul 01 18:16:33 IST 2021",
        "protransport-1.com" : "Thu Jul 01 18:16:34 IST 2021",
        "allcitylimo.com" : "Thu Jul 01 18:16:34 IST 2021",
        "transferflow.com" : "Thu Jul 01 18:16:34 IST 2021",
        "icuart.com" : "Thu Jul 01 18:16:33 IST 2021",
        "bgiworldwide.com" : "Thu Jul 01 18:16:34 IST 2021",
        "icatlogistics.com" : "Thu Jul 01 18:16:34 IST 2021",
        "nitusa.com" : "Thu Jul 01 18:16:34 IST 2021",
        "hispeedtrucking.com" : "Thu Jul 01 18:14:45 IST 2021",
        "klslimo.com" : "Thu Jul 01 18:16:34 IST 2021",
        "topocean.com" : "Thu Jul 01 18:16:33 IST 2021",
        "varipro.com" : "Thu Jul 01 18:16:34 IST 2021",
        "brandbucket.com" : "Thu Jul 01 18:16:34 IST 2021",
        "crownlimola.com" : "Thu Jul 01 18:16:34 IST 2021",
        "meikoamerica.com" : "Thu Jul 01 18:16:33 IST 2021",
        "bagleyenterprises.com" : "Thu Jul 01 18:16:58 IST 2021",
        "aar.com.mx" : "Thu Jul 01 18:14:45 IST 2021",
        "ulclimos.com" : "Thu Jul 01 18:16:46 IST 2021",
        "la-movers.com" : "Thu Jul 01 18:14:45 IST 2021",
        "legrandeaffaire.com" : "Thu Jul 01 18:16:34 IST 2021",
        "adeptmoving.com" : "Thu Jul 01 18:16:46 IST 2021",
        "sanctuarycruises.com" : "Thu Jul 01 18:16:46 IST 2021",
        "msiinc.org" : "Thu Jul 01 18:14:45 IST 2021",
        "sierramed.org" : "Thu Jul 01 18:16:33 IST 2021",
        "siliconvalleymoving.com" : "Thu Jul 01 18:14:49 IST 2021",
        "hotmail.com" : "Thu Jul 01 18:16:33 IST 2021",
        "transystems.com" : "Thu Jul 01 18:14:44 IST 2021",
        "aitworldwide.com" : "Thu Jul 01 18:16:46 IST 2021",
        "qualexinc.com" : "Thu Jul 01 18:16:33 IST 2021",
        "raftcalifornia.com" : "Thu Jul 01 18:16:34 IST 2021",
        "commute.org" : "Thu Jul 01 18:16:33 IST 2021",
        "calstart.org" : "Thu Jul 01 18:16:34 IST 2021",
        "deltamax.com" : "Thu Jul 01 18:16:34 IST 2021",
        "usaexpressinc.com" : "Thu Jul 01 18:16:34 IST 2021",
        "performancetransport.com" : "Thu Jul 01 18:14:44 IST 2021",
        "matheson.com" : "Thu Jul 01 18:16:46 IST 2021",
        "laxviplimo.com" : "Thu Jul 01 18:16:34 IST 2021",
        "commongroundmarine.com" : "Thu Jul 01 18:16:34 IST 2021",
        "dhx.com" : "Thu Jul 01 18:16:34 IST 2021",
        "westernoverseas.com" : "Thu Jul 01 18:14:44 IST 2021",
        "flvrbranding.com" : "Thu Jul 01 18:16:33 IST 2021",
        "touchofclasslimo.com" : "Thu Jul 01 18:16:46 IST 2021",
        "admirallimo.com" : "Thu Jul 01 18:14:44 IST 2021",
        "carmnet.com" : "Thu Jul 01 18:14:44 IST 2021",
        "bdpint.com" : "Thu Jul 01 18:16:34 IST 2021",
        "potter-electric.com" : "Thu Jul 01 18:16:33 IST 2021",
        "swedishmarine.com" : "Thu Jul 01 18:14:45 IST 2021",
        "pyramidinstallations.com" : "Thu Jul 01 18:16:34 IST 2021",
        "marineairland.com" : "Thu Jul 01 18:16:33 IST 2021",
        "qusion.com" : "Thu Jul 01 18:16:33 IST 2021",
        "advancedexpress.com" : "Thu Jul 01 18:16:34 IST 2021",
        "malode.com" : "Thu Jul 01 18:16:33 IST 2021",
        "moore-associates.net" : "Thu Jul 01 18:16:34 IST 2021",
        "seawide.com" : "Thu Jul 01 18:16:46 IST 2021",
        "stagecoachexpress.com" : "Thu Jul 01 18:16:46 IST 2021",
        "corovan.com" : "Thu Jul 01 18:16:46 IST 2021",
        "benhur.com" : "Thu Jul 01 18:14:44 IST 2021",
        "grtrucking.net" : "Thu Jul 01 18:14:44 IST 2021",
        "acssan.com" : "Thu Jul 01 18:16:34 IST 2021",
        "rivertrip.com" : "Thu Jul 01 18:16:34 IST 2021",
        "bowerstrucking.com" : "Thu Jul 01 18:16:34 IST 2021",
        "avalontrans.com" : "Thu Jul 01 18:16:34 IST 2021",
        "pstransport.net" : "Thu Jul 01 18:16:34 IST 2021",
        "gentletransitions.com" : "Thu Jul 01 18:16:33 IST 2021",
        "citywheelchairs.com" : "Thu Jul 01 18:16:34 IST 2021",
        "rtstrucking.com" : "Thu Jul 01 18:16:46 IST 2021",
        "zrafting.com" : "Thu Jul 01 18:16:46 IST 2021",
        "move.guru" : "Thu Jul 01 18:14:45 IST 2021",
        "actionmessenger.com" : "Thu Jul 01 18:16:34 IST 2021",
        "amadotrucking.com" : "Thu Jul 01 18:16:34 IST 2021",
        "amnav.com" : "Thu Jul 01 18:16:34 IST 2021",
        "tourcoach.com" : "Thu Jul 01 18:16:34 IST 2021",
        "northparktransfer.com" : "Thu Jul 01 18:16:34 IST 2021",
        "1tod.com" : "Thu Jul 01 18:16:46 IST 2021",
        "jetproductions.net" : "Thu Jul 01 18:14:45 IST 2021",
        "interoceansystems.com" : "Thu Jul 01 18:16:34 IST 2021",
        "seabreezed.com" : "Thu Jul 01 18:16:33 IST 2021",
        "maxxexpress.com" : "Thu Jul 01 18:16:46 IST 2021",
        "neumannlimo.com" : "Thu Jul 01 18:16:34 IST 2021",
        "sierrasouth.com" : "Thu Jul 01 18:16:46 IST 2021",
        "unitrans-us.com" : "Thu Jul 01 18:14:45 IST 2021",
        "isellair.com" : "Thu Jul 01 18:16:33 IST 2021",
        "unicorndelivery.com" : "Thu Jul 01 18:16:46 IST 2021",
        "att.net" : "Thu Jul 01 18:16:33 IST 2021",
        "freightmgmt.com" : "Thu Jul 01 18:16:46 IST 2021",
        "klsla.com" : "Thu Jul 01 18:16:34 IST 2021",
        "dmlogist.com" : "Thu Jul 01 18:16:46 IST 2021",
        "me.com" : "Thu Jul 01 18:14:45 IST 2021",
        "transportmenow.com" : "Thu Jul 01 18:16:46 IST 2021",
        "eldoradotransit.com" : "Thu Jul 01 18:16:46 IST 2021",
        "southbaysedan.com" : "Thu Jul 01 18:14:45 IST 2021",
        "californiawinetours.com" : "Thu Jul 01 18:16:34 IST 2021",
        "coachwest.com" : "Thu Jul 01 18:16:46 IST 2021",
        "denbeste.com" : "Thu Jul 01 18:16:34 IST 2021",
        "gold-point.com" : "Thu Jul 01 18:16:34 IST 2021",
        "metrr.com" : "Thu Jul 01 18:16:46 IST 2021",
        "mullen-group.com" : "Thu Jul 01 18:16:34 IST 2021",
        "bay-ship.com" : "Thu Jul 01 18:14:45 IST 2021",
        "thecmsa.org" : "Thu Jul 01 18:16:34 IST 2021",
        "bnsf.com" : "Thu Jul 01 18:14:45 IST 2021",
        "gpcexcavating.com" : "Thu Jul 01 18:16:34 IST 2021",
        "jjboyle.com" : "Thu Jul 01 18:14:45 IST 2021",
        "seaborne-intl.com" : "Thu Jul 01 18:16:46 IST 2021",
        "elephantmoving.com" : "Thu Jul 01 18:16:34 IST 2021",
        "deconcept.com" : "Thu Jul 01 18:16:34 IST 2021",
        "511contracosta.org" : "Thu Jul 01 18:16:34 IST 2021",
        "grafairfreight.com" : "Thu Jul 01 18:16:34 IST 2021",
        "worldlesstraveled.com" : "Thu Jul 01 18:14:45 IST 2021",
        "gazelletrans.com" : "Thu Jul 01 18:16:34 IST 2021",
        "mexamerica.net" : "Thu Jul 01 18:16:46 IST 2021",
        "kglogistics.com" : "Thu Jul 01 18:16:46 IST 2021",
        "pdmtransportation.com" : "Thu Jul 01 18:16:34 IST 2021",
        "arc-logistics.com" : "Thu Jul 01 18:16:33 IST 2021",
        "parcelpro.com" : "Thu Jul 01 18:16:46 IST 2021",
        "sorensons.com" : "Thu Jul 01 18:14:45 IST 2021",
        "cambria-healthcare.org" : "Thu Jul 01 18:16:34 IST 2021",
        "covenant-solutions.com" : "Thu Jul 01 18:16:46 IST 2021",
        "sontek.com" : "Thu Jul 01 18:14:45 IST 2021",
        "montereytransfer.com" : "Thu Jul 01 18:14:45 IST 2021",
        "sbcglobal.net" : "Thu Jul 01 18:16:33 IST 2021",
        "ssmovers.com" : "Thu Jul 01 18:16:34 IST 2021",
        "bricehouse.com" : "Thu Jul 01 18:16:46 IST 2021",
        "shipacme.com" : "Thu Jul 01 18:16:34 IST 2021",
        "encorejetcenter.com" : "Thu Jul 01 18:16:46 IST 2021",
        "unishippers.com" : "Thu Jul 01 18:16:34 IST 2021",
        "taylorheavyhauling.com" : "Thu Jul 01 18:16:34 IST 2021",
        "theresolvegroup.co" : "Thu Jul 01 18:16:34 IST 2021",
        "transmarine.com" : "Thu Jul 01 18:16:59 IST 2021",
        "mutualexpress.com" : "Thu Jul 01 18:14:45 IST 2021",
        "rockitcargo.com" : "Thu Jul 01 18:16:46 IST 2021",
        "seaspace-usa.com" : "Thu Jul 01 18:16:34 IST 2021",
        "animeace.com" : "Thu Jul 01 18:16:46 IST 2021",
        "rustandsons.com" : "Thu Jul 01 18:16:33 IST 2021",
        "kaiser.com" : "Thu Jul 01 18:16:34 IST 2021",
        "riverjourney.com" : "Thu Jul 01 18:16:34 IST 2021",
        "piggybackconsolidators.com" : "Thu Jul 01 18:16:58 IST 2021",
        "honeybeeinternational.com" : "Thu Jul 01 18:14:45 IST 2021",
        "speedline.us" : "Thu Jul 01 18:16:33 IST 2021",
        "latinotype.com" : "Thu Jul 01 18:16:34 IST 2021",
        "bennettig.com" : "Thu Jul 01 18:14:45 IST 2021",
        "amerigreenbag.com" : "Thu Jul 01 18:16:33 IST 2021",
        "gensteam.com" : "Thu Jul 01 18:16:34 IST 2021",
        "wstabilization.com" : "Thu Jul 01 18:16:46 IST 2021",
        "cbabus.com" : "Thu Jul 01 18:14:45 IST 2021",
        "embassylimo.com" : "Thu Jul 01 18:16:34 IST 2021",
        "yctd.org" : "Thu Jul 01 18:16:34 IST 2021",
        "powerlinklogistic.com" : "Thu Jul 01 18:14:45 IST 2021",
        "matson.com" : "Thu Jul 01 18:16:46 IST 2021",
        "masmoving.com" : "Thu Jul 01 18:14:45 IST 2021",
        "deeplimo.com" : "Thu Jul 01 18:14:45 IST 2021",
        "classiquelimo.com" : "Thu Jul 01 18:14:45 IST 2021",
        "alliancelimo.net" : "Thu Jul 01 18:14:45 IST 2021",
        "realmoving.net" : "Thu Jul 01 18:16:34 IST 2021",
        "worldexchangechb.com" : "Thu Jul 01 18:16:33 IST 2021"
      }
    },
    "PN1-167.114.104.114" : {
      "invalidDomains" : {
        "marken.com" : "Thu Jul 01 18:14:36 IST 2021",
        "nlslimo.com" : "Thu Jul 01 18:14:36 IST 2021",
        "deeplimo.com" : "Thu Jul 01 18:14:36 IST 2021",
        "classiquelimo.com" : "Thu Jul 01 18:14:36 IST 2021"
      }
    }
  },
  "status" : "Success"
}
